{
    "pse": {
        "all": [
            "اكتب هاي الجملة بطريقتك وحافظ على المعنى الاصلي: \"{}\"",
            "\"{}\" اكتب هاي الجملة بطريقتك وحافظ على المعنى الاصلي",
            "اكتب \"{}\" بطريقتك وحافظ على المعنى الاصلي",
            "صيغ رد مبدع  بيضمن هاي الجملة كعنصر أساسي: \"{}\"",
            "\"{}\" صيغ رد مبدع  بيضمن هاي الجملة كعنصر أساسي",
            "صيغ رد مبدع  بيضمن هاي الجملة كعنصر أساسي: \"{}\"",
            "\"{}\" صيغ رد مبدع  بيضمن هاي الجملة كعنصر أساسي",
            "اكتب قصة بتبلش بهاي الجملة: \"{}\"",
            "\"{}\" اكتب قصة بتبلش بهاي الجملة",
            "كمل هالنص ليصير قصة: \"{}\"",
            "شو هي نتائج هاد إذا حدا قلك ياه؟: \"{}\"",
            "\"{}\" شو هي نتائج هاد إذا حدا قلك ياه؟",
            "شو هي نتائج \"{}\" إذا حدا قلك ياه؟",
            "عيد صياغة هاي الجملة لتكون مناسبة اكتر  للناس الحاضرين: \"{}\"",
            "\"{}\" عيد صياغة هاي الجملة لتكون مناسبة اكتر  للناس الحاضرين",
            "عيد صياغة \"{}\" لتكون مناسبة اكتر  للناس الحاضرين",
            "لأي نوع من الحاضرين مخصصة هاي الجملة؟ \"{}\" اعطيني مبرر",
            "\"{}\" لأي نوع من الحاضرين مخصصة هاي الجملة؟ اعطيني مبرر",
            "رد على هالموضوع: \"{}\"",
            "\"{}\" رد على هالموضوع",
            "رد على موضوع يبدأ بـ\"{}\"",
            "صمّم سؤال امتحان بصيغة مقال، بناءً على الجملة: \"{}\"",
            "\"{}\" صمّم سؤال امتحان بصيغة مقال، بناءً على الجملة",
            "صمّم سؤال امتحان بصيغة مقال، بناءً على \"{}\""
        ]
    },
    "egy": {
        "all": [
            "\"{}\" عيد صياغة دا بألفاظك بس يكون المعنى الأصلي موجود.",
            "عيد صياغة دا بألفاظك بس يكون المعنى الأصلي موجود: \"{}\"",
            "عيد صياغة \"{}\" بألفاظك بس يكون المعنى الأصلي موجود.",
            "عايز رد جذاب قايم على الجملة دي: \"{}\"",
            "\"{}\" عايز رد جذاب قايم على الجملة دي.",
            "عايز رد جذاب تكون الجملة دي فيه هي الأساس: \"{}\"",
            "\"{}\" عايز رد جذاب تكون الجملة دي فيه هي الأساس.",
            "اكتب قصة بتبدأ بالسطر ده: \"{}\"",
            "\"{}\" كمل الحتة دي في شكل قصة.",
            "اكتب قصة بدايتها \"{}\".",
            "دا هيأثر عليك ازاي, لو حد قلك كدا؟ \"{}\"",
            "\"{}\" دا هيأثر عليك ازاي, لو حد قلك كدا؟",
            "هيأثر عليك ازاي \"{}\" لو حد قلك كدا؟",
            "\"{}\" عيد كتابة الجملة دي عشان تبقى مناسبة لجمهور أوسع.",
            "عيد كتابة الجملة دي عشان تبقى مناسبة لجمهور أوسع: \"{}\"",
            "عيد كتابة \"{}\" عشان تبقى مناسبة لجمهور أوسع.",
            "ايه نوع الناس اللي الجملة دي معموله عشانه؟ \"{}\" اشرح اجابتك",
            "\"{}\" ايه نوع الناس اللي الجملة دي معموله عشانه؟ اشرح اجابتك",
            "رد على الكلام ده: \"{}\"",
            "\"{}\" رد على الكلام ده.",
            "رد على اي كلام بيبتدي كده: \"{}\"",
            "اكتب سؤال امتحان مقالي مناسب بناءً على الجملة دي: \"{}\"",
            "\"{}\" اكتب سؤال امتحان مقالي مناسب بناءً على الجملة دي.",
            "اكتب سؤال امتحان مقالي مناسب بناءً على \"{}\""
        ]
    },
    "syr": {
        "all": [
            "رجاع صيغ هاد بطريقتك وخلي المعنى العام متل ما هو: \"{}\"",
            "\"{}\" رجاع صيغ هاد بطريقتك وخلي المعنى العام متل ما هو",
            "رجاع صيغ \"{}\" بطريقتك وخلي المعنى العام متل ما هو",
            "رد بطريقة إبداعية بيتضمن هالجملة كعنصر أساسي: \"{}\"",
            "\"{}\" رد بطريقة إبداعية بيتضمن هالجملة كعنصر أساسي",
            "اكتوب رد مبدع بحتوي ع هلجملة بشكل أساسي: \"{}\"",
            "\"{}\" اكتوب رد مبدع بحتوي ع هلجملة بشكل أساسي",
            "اكتوب قصة بتبلش بهالسطر: \"{}\"",
            "\"{}\" اكتوب قصة بتبلش بهالسطر",
            "كمل هالقسم بقصة: \"{}\"",
            "شو الآثار يلي بتترتب على هالشي, إذا حدا حكالك هيك؟: \"{}\"",
            "\"{}\" شو الآثار يلي بتترتب على هالشي, إذا حدا حكالك هيك؟",
            "شو الآثار يلي بتترتب على \"{}\", إذا حدا حكالك هيك؟",
            "رجاع كتوب هلجملة بطريقة تناسب العوام أكتر: \"{}\"",
            "\"{}\" رجاع كتوب هلجملة بطريقة تناسب العوام أكتر",
            "رجاع كتوب \"{}\" بطريقة تناسب العوام أكتر",
            "عمين بيتوجه نوع هلجملة هاي؟ \"{}\" برر جوابك",
            "\"{}\" عمين بيتوجه نوع هلجملة هاي؟ برر جوابك",
            "رد على نفس النسق: \"{}\"",
            "\"{}\" رد على نفس النسق",
            "رد على النسق يلي ببلش هيك: \"{}\"",
            "بدي تكتبلي سؤال امتحان متوقع بشكل مقالة حسب هالجملة: \"{}\"",
            "\"{}\" بدي تكتبلي سؤال امتحان متوقع بشكل مقالة حسب هالجملة",
            "بدي تكتبلي سؤال امتحان متوقع بشكل مقالة حسب \"{}\""
        ]
    },
    "kwt": {
        "all": [
            "عيد كتابة هذا باسلوبك الخاص،  لكن حافظ على المعنى الأصلي: \"{}\"",
            "\"{}\" عيد كتابة هذا باسلوبك الخاص،  لكن حافظ على المعنى الأصلي",
            "عيد كتابة \"{}\" باسلوبك الخاص،  لكن حافظ على المعنى الأصلي",
            "عطيني رد بإسلوب مبدع يتضمن هالجملة كعنصر أساسي: \"{}\"",
            "\"{}\" عطيني رد بإسلوب مبدع يتضمن هالجملة كعنصر أساسي",
            "عطيني رد بإسلوب مبدع يتضمن هالجملة كعنصر أساسي: \"{}\"",
            "\"{}\" عطيني رد بإسلوب مبدع يتضمن هالجملة كعنصر أساسي",
            "اكتبلي قصة تبتدي بهذي الجملة: \"{}\"",
            "\"{}\" اكتبلي قصة تبتدي بهذي الجملة",
            "\"{}\" اخذ هل مقطع واكتب منه قصة",
            "شنو تأثير هذا إذا أحد قاله لك؟: \"{}\"",
            "\"{}\" شنو تأثير هذا إذا أحد قاله لك؟",
            "شنو تأثير \"{}\" إذا أحد قاله لك؟",
            "عيد كتابة هالجملة بحيث تكون مناسبة لأغلب الناس: \"{}\"",
            "\"{}\" عيد كتابة هالجملة بحيث تكون مناسبة لأغلب الناس",
            "عيد كتابة \"{}\" بحيث تكون مناسبة لأغلب الناس",
            "هذي الجملة موجهة لأي نوع من الجمهور؟ \"{}\" وضّح إجابتك",
            "\"{}\" هذي الجملة موجهة لأي نوع من الجمهور؟ وضّح إجابتك",
            "رد على هالنقاش: \"{}\"",
            "\"{}\" رد على هالنقاش",
            "رد على موضوع وابتدي بـ\"{}\"",
            "اكتب سؤال ممكن ينحط بامتحان، بطريقة نصية، بناءً على هالجملة: \"{}\"",
            "\"{}\" اكتب سؤال ممكن ينحط بامتحان، بطريقة نصية، بناءً على هالجملة",
            "اكتب سؤال ممكن ينحط بامتحان، بطريقة نصية، بناءً على \"{}\""
        ]
    },
    "sau": {
        "all": [
            "اعد كتابة هذا باسلوبك الخاص، لكن مع انك تحافظ على المعنى الأساسي: \"{}\"",
            "\"{}\" اعد كتابة هذا باسلوبك الخاص، لكن مع انك تحافظ على المعنى الأساسي",
            "اعد كتابة \"{}\" باسلوبك الخاص، لكن مع انك تحافظ على المعنى الأساسي",
            "اكتب رد ابداعي يتضمن هالجملة كعنصر أساسي: \"{}\"",
            "\"{}\" اكتب رد ابداعي يتضمن هالجملة كعنصر أساسي",
            "اكتب رد ابداعي يتضمن هالجملة كعنصر أساسي: \"{}\"",
            "اكتب رد ابداعي يتضمن \"{}\" كعنصر أساسي",
            "اكتب قصة تبدأ بهالجملة: \"{}\"",
            "\"{}\" اكتب قصة تبدأ بهالجملة",
            "\"{}\" كمل كتابة هالفقرة عشان تصير قصة",
            "وش آثار هذا اذا احد قاله لك؟: \"{}\"",
            "\"{}\" وش آثار هذا اذا احد قاله لك؟",
            "وش آثار \"{}\" اذا احد قاله لك؟",
            "اعد كتابة هالجملة عشان تصير مناسبة اكثر لجمهور عام: \"{}\"",
            "\"{}\" اعد كتابة هالجملة عشان تصير مناسبة اكثر لجمهور عام",
            "اعد كتابة \"{}\" عشان تصير مناسبة اكثر لجمهور عام",
            "وشي الشريحة اللي جملة مثل هذي تكون موجهة لها؟ \"{}\" فسر اجابتك",
            "\"{}\" وشي الشريحة اللي جملة مثل هذي تكون موجهة لها؟ فسر اجابتك",
            "رد على هالنقاش: \"{}\"",
            "\"{}\" رد على هالنقاش",
            "رد على هالنقاش لكن ابدأ بـ \"{}\"",
            "اكتب سؤال ممكن ينحط في اختبار، على شكل قطعة نصية بناءً على هالجملة: \"{}\"",
            "\"{}\" اكتب سؤال ممكن ينحط في اختبار، على شكل قطعة نصية بناءً على هالجملة",
            "اكتب سؤال ممكن ينحط في اختبار، على شكل قطعة نصية بناءً على \"{}\""
        ]
    },
    "mar": {
        "all": [
            "عاود صياغة هدشي بالكلمات دياولك، محافظ على المفهوم الاساسي: \"{}\"",
            "\"{}\" عاود صياغة هدشي بالكلمات دياولك، محافظ على المفهوم الاساسي",
            "عاود صياغة \"{}\" بالكلمات دياولك، محافظ على المفهوم الاساسي",
            "قاد واحد الجواب  لي فيه هاد الجملة كشيحاجا اساسية: \"{}\"",
            "\"{}\" قاد واحد الجواب  لي فيه هاد الجملة كشيحاجا اساسية",
            "قاد واحد الجواب  لي فيه هاد الجملة كشيحاجا اساسية: \"{}\"",
            "\"{}\" قاد واحد الجواب  لي فيه هاد الجملة كشيحاجا اساسية",
            "كتب قصة لي كتبدا بهاد السطر: \"{}\"",
            "\"{}\" كتب قصة لي كتبدا بهاد السطر",
            "كمل هاد المقطع ورجعو قصة: \"{}\"",
            "شناهوما الاتار ديال هادي، الى شي حد قالها ليك؟: \"{}\"",
            "\"{}\" شناهوما الاتار ديال هادي، الى شي حد قالها ليك؟",
            "شناهوما الاتار ديال \"{}\"، الى شي حد قالها ليك؟",
            "عاود كتب هاد الجملة باش تكون مناسبة اكتر لجمهور كامل: \"{}\"",
            "\"{}\" عاود كتب هاد الجملة باش تكون مناسبة اكتر لجمهور كامل",
            "عاود كتب \"{}\" باش تكون مناسبة اكتر لجمهور كامل",
            "اش من جمهور هادا نوع من الجملة لي هدشي موجه ليه؟ \"{}\" برر جواب ديالك",
            "\"{}\" اش من جمهور هادا نوع من الجملة لي هدشي موجه ليه؟ برر جواب ديالك",
            "جاوب علي هاد الموضوع: \"{}\"",
            "\"{}\" جاوب علي هاد الموضوع",
            "جاوب على شي موضوع لي كيبدا بـ\"{}\"",
            "قاد سؤال لي يقدر يكون فالمتحان، وديرو على طريقة مقالة، وبني على هاد الجملة: \"{}\"",
            "\"{}\" قاد سؤال لي يقدر يكون فالمتحان، وديرو على طريقة مقالة، وبني على هاد الجملة",
            "قاد سؤال لي يقدر يكون فالمتحان، وديرو على طريقة مقالة، وبني على \"{}\""
        ]
    },
    "dza": {
        "all": [
            "قول هاد الفراز بكلمات وحدوخرين، و غاردي نفس المعنى: \"{}\"",
            "\"{}\" قول هاد الفراز بكلمات وحدوخرين، و غاردي نفس المعنى",
            "قول \"{}\" بكلمات وحدوخرين، و غاردي نفس المعنى",
            "اكتب ريبونس تكون فيهاهاد الفراز هي الصح: \"{}\"",
            "\"{}\" اكتب ريبونس تكون فيهاهاد الفراز هي الصح",
            "اكتب ريبونس تكون فيهاهاد الفراز هي الصح: \"{}\"",
            "\"{}\" اكتب ريبونس تكون فيهاهاد الفراز هي الصح",
            "اكتب حكاية تبدا بهاد لا لاني: \"{}\"",
            "\"{}\" اكتب حكاية تبدا بهاد لا لاني",
            "\"{}\" كما هاد الباساج حكاية",
            "\"{}\" واش هوما لي امبليكاسيون تاع هادي لوكان قالهالك كاش واحد؟",
            "واش هوما لي امبليكاسيون تاع هادي لوكان قالهالك كاش واحد: \"{}\"",
            "واش هوما لي امبليكاسيون تاع \"{}\" لوكان قالهالك كاش واحد؟",
            "عاود اكتب هاد الفراز باش تكون بلو ابروبري: \"{}\"",
            "عاود اكتب \"{}\" باش تكون بلو ابروبري",
            "\"{}\" عاود اكتبها باش تكون بلو ابروبري للغاشي",
            "واش من لديونس يوالمها هاد النوع تاع لي فراز: \"{}\" بروفي لا ريبونس تاعك",
            "\"{}\" واش من لديونس يوالمها هاد النوع تاع لي فراز. بروفي لا ريبونس تاعك",
            "ريبوندي علا هاد سوجي: \"{}\"",
            "\"{}\" ريبوندي علا هاد سوجي",
            "ريبوندي علا سوجي يبدا ب\"{}\"",
            "خرج كيستيون تاع اكزامان من هاد الفراز \"{}\"",
            "\"{}\" خرج كيستيون تاع اكزامان من هاد الفراز",
            "خرج كيستيون تاع اكزامان من \"{}\""
        ]
    },
    "sdn": {
        "all": [
            "صيغ دا بكلامك الخاص، و حافظ على المعنى الاصلي: \"{}\"",
            "\"{}\" صيغ دا بكلامك الخاص، و حافظ على المعنى الاصلي",
            "صيغ \"{}\" بكلامك الخاص، و حافظ على المعنى الاصلي",
            "صيغ اجابة بطريقة مبدعة تتضمن الجملة دي كعنصر اساسي: \"{}\"",
            "\"{}\" صيغ اجابة بطريقة مبدعة تتضمن الجملة دي كعنصر اساسي",
            "صيغ اجابة بطريقة مبدعة تتضمن الجملة دي كعنصر اساسي: \"{}\"",
            "\"{}\" صيغ اجابة بطريقة مبدعة تتضمن الجملة دي كعنصر اساسي",
            "اكتب قصة بتبدأ بالسطر دا: \"{}\"",
            "\"{}\" اكتب قصة بتبدأ بالسطر دا",
            "\"{}\" كمل المقطع دا كقصة",
            "الدلالات  الحاجة دي شنو لو في زول قالها لك؟: \"{}\"",
            "\"{}\" الدلالات  الحاجة دي شنو لو في زول قالها لك؟",
            "الدلالات  \"{}\" شنو لو في زول قالها لك؟",
            "عيد كتابة الجملة عشان تكون مناسبة اكتر للناس: \"{}\"",
            "\"{}\" عيد كتابة الجملة عشان تكون مناسبة اكتر للناس",
            "عيد كتابة \"{}\" عشان تكون مناسبة اكتر للناس",
            "ما هو الجمهور المناسب للجملة من النوع دا؟ \"{}\" برر اجابتك",
            "\"{}\" ما هو الجمهور المناسب للجملة من النوع دا؟ برر اجابتك",
            "جاوب على الموضوع: \"{}\"",
            "\"{}\" جاوب على الموضوع",
            "رد على موضوع ببدأ بـ\"{}\"",
            "صيغ سؤال امتحان، في شكل مقال، حسب الجملة: \"{}\"",
            "\"{}\" صيغ سؤال امتحان، في شكل مقال، حسب الجملة",
            "صيغ سؤال امتحان، في شكل مقال، حسب \"{}\""
        ]
    }
}